{"editions":{"java":{"name":"Java Edition","versions":[{"name":"1.18 Experimental 1","protocolNumber":1073741865,"dataNumber":2825},{"name":"1.17.1","protocolNumber":756,"dataNumber":2730},{"name":"1.17.1-rc2","protocolNumber":1073741864,"dataNumber":2729},{"name":"1.17.1-rc1","protocolNumber":1073741863,"dataNumber":2728},{"name":"1.17.1-pre3","protocolNumber":1073741862,"dataNumber":2727},{"name":"1.17.1-pre2","protocolNumber":1073741861,"dataNumber":2726},{"name":"1.17.1-pre1","protocolNumber":1073741860,"dataNumber":2725},{"name":"1.17","protocolNumber":755,"dataNumber":2724},{"name":"1.17-rc2","protocolNumber":1073741859,"dataNumber":2723},{"name":"1.17-rc1","protocolNumber":1073741858,"dataNumber":2722},{"name":"1.17-pre5","protocolNumber":1073741857,"dataNumber":2721},{"name":"1.17-pre4","protocolNumber":1073741856,"dataNumber":2720},{"name":"1.17-pre3","protocolNumber":1073741855,"dataNumber":2719},{"name":"1.17-pre2","protocolNumber":1073741854,"dataNumber":2718},{"name":"1.17-pre1","protocolNumber":1073741853,"dataNumber":2716},{"name":"21w20a","protocolNumber":1073741852,"dataNumber":2715},{"name":"21w19a","protocolNumber":1073741851,"dataNumber":2714},{"name":"21w18a","protocolNumber":1073741850,"dataNumber":2713},{"name":"21w17a","protocolNumber":1073741849,"dataNumber":2712},{"name":"21w16a","protocolNumber":1073741847,"dataNumber":2711},{"name":"21w15a","protocolNumber":1073741846,"dataNumber":2709},{"name":"21w14a","protocolNumber":1073741845,"dataNumber":2706},{"name":"21w13a","protocolNumber":1073741844,"dataNumber":2705},{"name":"21w11a","protocolNumber":1073741843,"dataNumber":2703},{"name":"21w10a","protocolNumber":1073741842,"dataNumber":2699},{"name":"21w08b","protocolNumber":1073741841,"dataNumber":2698},{"name":"21w08a","protocolNumber":1073741840,"dataNumber":2697},{"name":"21w07a","protocolNumber":1073741839,"dataNumber":2695},{"name":"21w06a","protocolNumber":1073741838,"dataNumber":2694},{"name":"21w05b","protocolNumber":1073741837,"dataNumber":2692},{"name":"21w05a","protocolNumber":1073741836,"dataNumber":2690},{"name":"21w03a","protocolNumber":1073741835,"dataNumber":2689},{"name":"20w51a","protocolNumber":1073741833,"dataNumber":2687},{"name":"20w49a","protocolNumber":1073741832,"dataNumber":2685},{"name":"20w48a","protocolNumber":1073741831,"dataNumber":2683},{"name":"20w46a","protocolNumber":1073741830,"dataNumber":2682},{"name":"20w45a","protocolNumber":1073741829,"dataNumber":2681},{"name":"Combat Test 8c","protocolNumber":803,"dataNumber":2707},{"name":"Combat Test 8b","protocolNumber":803,"dataNumber":2706},{"name":"Combat Test 7c","protocolNumber":802,"dataNumber":2704},{"name":"Combat Test 7b","protocolNumber":802,"dataNumber":2703},{"name":"Combat Test 7","protocolNumber":802,"dataNumber":2702},{"name":"Combat Test 6","protocolNumber":801,"dataNumber":2701},{"name":"1.16.5","protocolNumber":754,"dataNumber":2586},{"name":"1.16.5-rc1","protocolNumber":1073741834,"dataNumber":2585},{"name":"1.16.4","protocolNumber":754,"dataNumber":2584},{"name":"1.16.4-rc1","protocolNumber":1073741827,"dataNumber":2583},{"name":"1.16.4-pre2","protocolNumber":1073741826,"dataNumber":2582},{"name":"1.16.4-pre1","protocolNumber":1073741825,"dataNumber":2581},{"name":"1.16.3","protocolNumber":753,"dataNumber":2580},{"name":"1.16.3-rc1","protocolNumber":752,"dataNumber":2579},{"name":"1.16.2","protocolNumber":751,"dataNumber":2578},{"name":"1.16.2-rc2","protocolNumber":750,"dataNumber":2577},{"name":"1.16.2-rc1","protocolNumber":749,"dataNumber":2576},{"name":"1.16.2-pre3","protocolNumber":748,"dataNumber":2575},{"name":"1.16.2-pre2","protocolNumber":746,"dataNumber":2574},{"name":"1.16.2-pre1","protocolNumber":744,"dataNumber":2573},{"name":"20w30a","protocolNumber":742,"dataNumber":2572},{"name":"20w29a","protocolNumber":741,"dataNumber":2571},{"name":"20w28a","protocolNumber":740,"dataNumber":2570},{"name":"20w27a","protocolNumber":738,"dataNumber":2569},{"name":"1.16.1","protocolNumber":736,"dataNumber":2567},{"name":"1.16","protocolNumber":735,"dataNumber":2566},{"name":"1.16-rc1","protocolNumber":734,"dataNumber":2565},{"name":"1.16-pre8","protocolNumber":733,"dataNumber":2564},{"name":"1.16-pre7","protocolNumber":732,"dataNumber":2563},{"name":"1.16-pre6","protocolNumber":730,"dataNumber":2562},{"name":"1.16-pre5","protocolNumber":729,"dataNumber":2561},{"name":"1.16-pre4","protocolNumber":727,"dataNumber":2560},{"name":"1.16-pre3","protocolNumber":725,"dataNumber":2559},{"name":"1.16-pre2","protocolNumber":722,"dataNumber":2557},{"name":"1.16-pre1","protocolNumber":721,"dataNumber":2556},{"name":"20w22a","protocolNumber":719,"dataNumber":2555},{"name":"20w21a","protocolNumber":718,"dataNumber":2554},{"name":"20w20b","protocolNumber":717,"dataNumber":2537},{"name":"20w20a","protocolNumber":716,"dataNumber":2536},{"name":"20w19a","protocolNumber":715,"dataNumber":2534},{"name":"20w18a","protocolNumber":714,"dataNumber":2532},{"name":"20w17a","protocolNumber":713,"dataNumber":2529},{"name":"20w16a","protocolNumber":712,"dataNumber":2526},{"name":"20w15a","protocolNumber":711,"dataNumber":2525},{"name":"20w14a","protocolNumber":710,"dataNumber":2524},{"name":"20w13b","protocolNumber":709,"dataNumber":2521},{"name":"20w13a","protocolNumber":708,"dataNumber":2520},{"name":"20w12a","protocolNumber":707,"dataNumber":2515},{"name":"20w11a","protocolNumber":706,"dataNumber":2513},{"name":"20w10a","protocolNumber":705,"dataNumber":2512},{"name":"20w09a","protocolNumber":704,"dataNumber":2510},{"name":"20w08a","protocolNumber":703,"dataNumber":2507},{"name":"20w07a","protocolNumber":702,"dataNumber":2506},{"name":"20w06a","protocolNumber":701,"dataNumber":2504},{"name":"Combat Test 5","protocolNumber":601,"dataNumber":2321},{"name":"Combat Test 4","protocolNumber":600,"dataNumber":2320},{"name":"1.15.2","protocolNumber":578,"dataNumber":2230},{"name":"1.15.2-pre2","protocolNumber":577,"dataNumber":2229},{"name":"1.15.2 Pre-Release 1","protocolNumber":576,"dataNumber":2228},{"name":"1.15.1","protocolNumber":575,"dataNumber":2227},{"name":"1.15.1-pre1","protocolNumber":574,"dataNumber":2226},{"name":"1.15","protocolNumber":573,"dataNumber":2225},{"name":"1.15-pre7","protocolNumber":572,"dataNumber":2224},{"name":"1.15-pre6","protocolNumber":571,"dataNumber":2223},{"name":"1.15-pre5","protocolNumber":570,"dataNumber":2222},{"name":"1.15-pre4","protocolNumber":569,"dataNumber":2221},{"name":"1.15-pre3","protocolNumber":567,"dataNumber":2220},{"name":"1.15 Pre-Release 2","protocolNumber":566,"dataNumber":2219},{"name":"1.15-pre1","protocolNumber":565,"dataNumber":2218},{"name":"19w46b","protocolNumber":564,"dataNumber":2217},{"name":"19w46a","protocolNumber":563,"dataNumber":2216},{"name":"19w45b","protocolNumber":562,"dataNumber":2215},{"name":"19w45a","protocolNumber":561,"dataNumber":2214},{"name":"19w44a","protocolNumber":560,"dataNumber":2213},{"name":"19w42a","protocolNumber":559,"dataNumber":2212},{"name":"19w41a","protocolNumber":558,"dataNumber":2210},{"name":"19w40a","protocolNumber":557,"dataNumber":2208},{"name":"19w39a","protocolNumber":556,"dataNumber":2207},{"name":"19w38b","protocolNumber":555,"dataNumber":2206},{"name":"19w38a","protocolNumber":554,"dataNumber":2205},{"name":"19w37a","protocolNumber":553,"dataNumber":2204},{"name":"19w36a","protocolNumber":552,"dataNumber":2203},{"name":"19w35a","protocolNumber":551,"dataNumber":2201},{"name":"19w34a","protocolNumber":550,"dataNumber":2200},{"name":"Combat Test 3","protocolNumber":502,"dataNumber":2069},{"name":"Combat Test 2","protocolNumber":501,"dataNumber":2068},{"name":"1.14.3 - Combat Test","protocolNumber":500,"dataNumber":2067},{"name":"1.14.4","protocolNumber":498,"dataNumber":1976},{"name":"1.14.4 Pre-Release 7","protocolNumber":497,"dataNumber":1975},{"name":"1.14.4 Pre-Release 6","protocolNumber":496,"dataNumber":1974},{"name":"1.14.4 Pre-Release 5","protocolNumber":495,"dataNumber":1973},{"name":"1.14.4 Pre-Release 4","protocolNumber":494,"dataNumber":1972},{"name":"1.14.4 Pre-Release 3","protocolNumber":493,"dataNumber":1971},{"name":"1.14.4 Pre-Release 2","protocolNumber":492,"dataNumber":1970},{"name":"1.14.4 Pre-Release 1","protocolNumber":491,"dataNumber":1969},{"name":"1.14.3","protocolNumber":490,"dataNumber":1968},{"name":"1.14.3 Pre-Release 4","protocolNumber":489,"dataNumber":1967},{"name":"1.14.3 Pre-Release 3","protocolNumber":488,"dataNumber":1966},{"name":"1.14.3 Pre-Release 2","protocolNumber":487,"dataNumber":1965},{"name":"1.14.3 Pre-Release 1","protocolNumber":486,"dataNumber":1964},{"name":"1.14.2","protocolNumber":485,"dataNumber":1963},{"name":"1.14.2 Pre-Release 4","protocolNumber":484,"dataNumber":1962},{"name":"1.14.2 Pre-Release 3","protocolNumber":483,"dataNumber":1960},{"name":"1.14.2 Pre-Release 2","protocolNumber":482,"dataNumber":1959},{"name":"1.14.2 Pre-Release 1","protocolNumber":481,"dataNumber":1958},{"name":"1.14.1","protocolNumber":480,"dataNumber":1957},{"name":"1.14.1 Pre-Release 2","protocolNumber":479,"dataNumber":1956},{"name":"1.14.1 Pre-Release 1","protocolNumber":478,"dataNumber":1955},{"name":"1.14","protocolNumber":477,"dataNumber":1952},{"name":"1.14 Pre-Release 5","protocolNumber":476,"dataNumber":1951},{"name":"1.14 Pre-Release 4","protocolNumber":475,"dataNumber":1950},{"name":"1.14 Pre-Release 3","protocolNumber":474,"dataNumber":1949},{"name":"1.14 Pre-Release 2","protocolNumber":473,"dataNumber":1948},{"name":"1.14 Pre-Release 1","protocolNumber":472,"dataNumber":1947},{"name":"19w14b","protocolNumber":471,"dataNumber":1945},{"name":"19w14a","protocolNumber":470,"dataNumber":1944},{"name":"19w13b","protocolNumber":469,"dataNumber":1943},{"name":"19w13a","protocolNumber":468,"dataNumber":1942},{"name":"19w12b","protocolNumber":467,"dataNumber":1941},{"name":"19w12a","protocolNumber":466,"dataNumber":1940},{"name":"19w11b","protocolNumber":465,"dataNumber":1938},{"name":"19w11a","protocolNumber":464,"dataNumber":1937},{"name":"19w09a","protocolNumber":463,"dataNumber":1935},{"name":"19w08b","protocolNumber":462,"dataNumber":1934},{"name":"19w08a","protocolNumber":461,"dataNumber":1933},{"name":"19w07a","protocolNumber":460,"dataNumber":1932},{"name":"19w06a","protocolNumber":459,"dataNumber":1931},{"name":"19w05a","protocolNumber":458,"dataNumber":1930},{"name":"19w04b","protocolNumber":457,"dataNumber":1927},{"name":"19w04a","protocolNumber":456,"dataNumber":1926},{"name":"19w03c","protocolNumber":455,"dataNumber":1924},{"name":"19w03b","protocolNumber":454,"dataNumber":1923},{"name":"19w03a","protocolNumber":453,"dataNumber":1922},{"name":"19w02a","protocolNumber":452,"dataNumber":1921},{"name":"18w50a","protocolNumber":451,"dataNumber":1919},{"name":"18w49a","protocolNumber":450,"dataNumber":1916},{"name":"18w48b","protocolNumber":449,"dataNumber":1915},{"name":"18w48a","protocolNumber":448,"dataNumber":1914},{"name":"18w47b","protocolNumber":447,"dataNumber":1913},{"name":"18w47a","protocolNumber":446,"dataNumber":1912},{"name":"18w46a","protocolNumber":445,"dataNumber":1910},{"name":"18w45a","protocolNumber":444,"dataNumber":1908},{"name":"18w44a","protocolNumber":443,"dataNumber":1907},{"name":"18w43c","protocolNumber":442,"dataNumber":1903},{"name":"18w43b","protocolNumber":441,"dataNumber":1902},{"name":"18w43a","protocolNumber":440,"dataNumber":1901},{"name":"1.13.2","protocolNumber":404,"dataNumber":1631},{"name":"1.13.2-pre2","protocolNumber":403,"dataNumber":1630},{"name":"1.13.2-pre1","protocolNumber":402,"dataNumber":1629},{"name":"1.13.1","protocolNumber":401,"dataNumber":1628},{"name":"1.13.1-pre2","protocolNumber":400,"dataNumber":1627},{"name":"1.13.1-pre1","protocolNumber":399,"dataNumber":1626},{"name":"18w33a","protocolNumber":398,"dataNumber":1625},{"name":"18w32a","protocolNumber":397,"dataNumber":1623},{"name":"18w31a","protocolNumber":396,"dataNumber":1622},{"name":"18w30b","protocolNumber":395,"dataNumber":1621},{"name":"18w30a","protocolNumber":394,"dataNumber":1620},{"name":"1.13","protocolNumber":393,"dataNumber":1519},{"name":"1.13-pre10","protocolNumber":392,"dataNumber":1518},{"name":"1.13-pre9","protocolNumber":391,"dataNumber":1517},{"name":"1.13-pre8","protocolNumber":390,"dataNumber":1516},{"name":"1.13-pre7","protocolNumber":389,"dataNumber":1513},{"name":"1.13-pre6","protocolNumber":388,"dataNumber":1512},{"name":"1.13-pre5","protocolNumber":387,"dataNumber":1511},{"name":"1.13-pre4","protocolNumber":386,"dataNumber":1504},{"name":"1.13-pre3","protocolNumber":385,"dataNumber":1503},{"name":"1.13-pre2","protocolNumber":384,"dataNumber":1502},{"name":"1.13-pre1","protocolNumber":383,"dataNumber":1501},{"name":"18w22c","protocolNumber":382,"dataNumber":1499},{"name":"18w22b","protocolNumber":381,"dataNumber":1498},{"name":"18w22a","protocolNumber":380,"dataNumber":1497},{"name":"18w21b","protocolNumber":379,"dataNumber":1496},{"name":"18w21a","protocolNumber":378,"dataNumber":1495},{"name":"18w20c","protocolNumber":377,"dataNumber":1493},{"name":"18w20b","protocolNumber":376,"dataNumber":1491},{"name":"18w20a","protocolNumber":375,"dataNumber":1489},{"name":"18w19b","protocolNumber":374,"dataNumber":1485},{"name":"18w19a","protocolNumber":373,"dataNumber":1484},{"name":"18w16a","protocolNumber":372,"dataNumber":1483},{"name":"18w15a","protocolNumber":371,"dataNumber":1482},{"name":"18w14b","protocolNumber":370,"dataNumber":1481},{"name":"18w14a","protocolNumber":369,"dataNumber":1479},{"name":"18w11a","protocolNumber":368,"dataNumber":1478},{"name":"18w10d","protocolNumber":367,"dataNumber":1477},{"name":"18w10c","protocolNumber":366,"dataNumber":1476},{"name":"18w10b","protocolNumber":365,"dataNumber":1474},{"name":"18w10a","protocolNumber":364,"dataNumber":1473},{"name":"18w09a","protocolNumber":363,"dataNumber":1472},{"name":"18w08b","protocolNumber":362,"dataNumber":1471},{"name":"18w08a","protocolNumber":361,"dataNumber":1470},{"name":"18w07c","protocolNumber":360,"dataNumber":1469},{"name":"18w07b","protocolNumber":359,"dataNumber":1468},{"name":"18w07a","protocolNumber":358,"dataNumber":1467},{"name":"18w06a","protocolNumber":357,"dataNumber":1466},{"name":"18w05a","protocolNumber":356,"dataNumber":1464},{"name":"18w03b","protocolNumber":355,"dataNumber":1463},{"name":"18w03a","protocolNumber":354,"dataNumber":1462},{"name":"18w02a","protocolNumber":353,"dataNumber":1461},{"name":"18w01a","protocolNumber":352,"dataNumber":1459},{"name":"17w50a","protocolNumber":351,"dataNumber":1457},{"name":"17w49b","protocolNumber":350,"dataNumber":1455},{"name":"17w49a","protocolNumber":349,"dataNumber":1454},{"name":"17w48a","protocolNumber":348,"dataNumber":1453},{"name":"17w47b","protocolNumber":347,"dataNumber":1452},{"name":"17w47a","protocolNumber":346,"dataNumber":1451},{"name":"17w46a","protocolNumber":345,"dataNumber":1449},{"name":"17w45b","protocolNumber":344,"dataNumber":1448},{"name":"17w45a","protocolNumber":343,"dataNumber":1447},{"name":"17w43b","protocolNumber":342,"dataNumber":1445},{"name":"17w43a","protocolNumber":341,"dataNumber":1444},{"name":"1.12.2","protocolNumber":340,"dataNumber":1343},{"name":"1.12.2-pre2","protocolNumber":339,"dataNumber":1342},{"name":"1.12.2-pre1","protocolNumber":339,"dataNumber":1341},{"name":"1.12.1","protocolNumber":338,"dataNumber":1241},{"name":"1.12.1-pre1","protocolNumber":337,"dataNumber":1240},{"name":"17w31a","protocolNumber":336,"dataNumber":1239},{"name":"1.12","protocolNumber":335,"dataNumber":1139},{"name":"1.12-pre7","protocolNumber":334,"dataNumber":1138},{"name":"1.12-pre6","protocolNumber":333,"dataNumber":1137},{"name":"1.12-pre5","protocolNumber":332,"dataNumber":1136},{"name":"1.12-pre4","protocolNumber":331,"dataNumber":1135},{"name":"1.12-pre3","protocolNumber":330,"dataNumber":1134},{"name":"1.12-pre2","protocolNumber":329,"dataNumber":1133},{"name":"1.12-pre1","protocolNumber":328,"dataNumber":1132},{"name":"17w18b","protocolNumber":327,"dataNumber":1131},{"name":"17w18a","protocolNumber":326,"dataNumber":1130},{"name":"17w17b","protocolNumber":325,"dataNumber":1129},{"name":"17w17a","protocolNumber":324,"dataNumber":1128},{"name":"17w16b","protocolNumber":323,"dataNumber":1127},{"name":"17w16a","protocolNumber":322,"dataNumber":1126},{"name":"17w15a","protocolNumber":321,"dataNumber":1125},{"name":"17w14a","protocolNumber":320,"dataNumber":1124},{"name":"17w13b","protocolNumber":319,"dataNumber":1123},{"name":"17w13a","protocolNumber":318,"dataNumber":1122},{"name":"17w06a","protocolNumber":317,"dataNumber":1022},{"name":"1.11.2","protocolNumber":316,"dataNumber":922},{"name":"1.11.1","protocolNumber":316,"dataNumber":921},{"name":"16w50a","protocolNumber":316,"dataNumber":920},{"name":"1.11","protocolNumber":315,"dataNumber":819},{"name":"1.11-pre1","protocolNumber":314,"dataNumber":818},{"name":"16w44a","protocolNumber":313,"dataNumber":817},{"name":"16w43a","protocolNumber":313,"dataNumber":816},{"name":"16w42a","protocolNumber":312,"dataNumber":815},{"name":"16w41a","protocolNumber":311,"dataNumber":814},{"name":"16w40a","protocolNumber":310,"dataNumber":813},{"name":"16w39c","protocolNumber":309,"dataNumber":812},{"name":"16w39b","protocolNumber":308,"dataNumber":811},{"name":"16w39a","protocolNumber":307,"dataNumber":809},{"name":"16w38a","protocolNumber":306,"dataNumber":807},{"name":"16w36a","protocolNumber":305,"dataNumber":805},{"name":"16w35a","protocolNumber":304,"dataNumber":803},{"name":"16w33a","protocolNumber":303,"dataNumber":802},{"name":"16w32b","protocolNumber":302,"dataNumber":801},{"name":"16w32a","protocolNumber":301,"dataNumber":800},{"name":"1.10.2","protocolNumber":210,"dataNumber":512},{"name":"1.10.1","protocolNumber":210,"dataNumber":511},{"name":"1.10","protocolNumber":210,"dataNumber":510},{"name":"1.10-pre2","protocolNumber":205,"dataNumber":507},{"name":"1.10-pre1","protocolNumber":204,"dataNumber":506},{"name":"16w21b","protocolNumber":203,"dataNumber":504},{"name":"16w21a","protocolNumber":202,"dataNumber":503},{"name":"16w20a","protocolNumber":201,"dataNumber":501},{"name":"1.9.4","protocolNumber":110,"dataNumber":184},{"name":"1.9.3","protocolNumber":110,"dataNumber":183},{"name":"1.9.3-pre3","protocolNumber":110,"dataNumber":182},{"name":"1.9.3-pre2","protocolNumber":110,"dataNumber":181},{"name":"1.9.3-pre1","protocolNumber":109,"dataNumber":180},{"name":"16w15b","protocolNumber":109,"dataNumber":179},{"name":"16w15a","protocolNumber":109,"dataNumber":178},{"name":"16w14a","protocolNumber":109,"dataNumber":177},{"name":"1.9.2","protocolNumber":109,"dataNumber":176},{"name":"1.9.1","protocolNumber":108,"dataNumber":175},{"name":"1.9.1-pre3","protocolNumber":108,"dataNumber":172},{"name":"1.9.1-pre2","protocolNumber":108,"dataNumber":171},{"name":"1.9.1-pre1","protocolNumber":107,"dataNumber":170},{"name":"1.9","protocolNumber":107,"dataNumber":169},{"name":"1.9-pre4","protocolNumber":106,"dataNumber":168},{"name":"1.9-pre3","protocolNumber":105,"dataNumber":167},{"name":"1.9-pre2","protocolNumber":104,"dataNumber":165},{"name":"1.9-pre1","protocolNumber":103,"dataNumber":164},{"name":"16w07b","protocolNumber":102,"dataNumber":163},{"name":"16w07a","protocolNumber":101,"dataNumber":162},{"name":"16w06a","protocolNumber":100,"dataNumber":161},{"name":"16w05b","protocolNumber":99,"dataNumber":160},{"name":"16w05a","protocolNumber":98,"dataNumber":159},{"name":"16w04a","protocolNumber":97,"dataNumber":158},{"name":"16w03a","protocolNumber":96,"dataNumber":157},{"name":"16w02a","protocolNumber":95,"dataNumber":156},{"name":"15w51b","protocolNumber":94,"dataNumber":155},{"name":"15w51a","protocolNumber":93,"dataNumber":154},{"name":"15w50a","protocolNumber":92,"dataNumber":153},{"name":"15w49b","protocolNumber":91,"dataNumber":152},{"name":"15w49a","protocolNumber":90,"dataNumber":151},{"name":"15w47c","protocolNumber":89,"dataNumber":150},{"name":"15w47b","protocolNumber":88,"dataNumber":149},{"name":"15w47a","protocolNumber":87,"dataNumber":148},{"name":"15w46a","protocolNumber":86,"dataNumber":146},{"name":"15w45a","protocolNumber":85,"dataNumber":145},{"name":"15w44b","protocolNumber":84,"dataNumber":143},{"name":"15w44a","protocolNumber":83,"dataNumber":142},{"name":"15w43c","protocolNumber":82,"dataNumber":141},{"name":"15w43b","protocolNumber":81,"dataNumber":140},{"name":"15w43a","protocolNumber":80,"dataNumber":139},{"name":"15w42a","protocolNumber":79,"dataNumber":138},{"name":"15w41b","protocolNumber":78,"dataNumber":137},{"name":"15w41a","protocolNumber":77,"dataNumber":136},{"name":"15w40b","protocolNumber":76,"dataNumber":134},{"name":"15w40a","protocolNumber":75,"dataNumber":133},{"name":"15w39c","protocolNumber":74,"dataNumber":132},{"name":"15w39b","protocolNumber":74,"dataNumber":131},{"name":"15w39a","protocolNumber":74,"dataNumber":130},{"name":"15w38b","protocolNumber":73,"dataNumber":129},{"name":"15w38a","protocolNumber":72,"dataNumber":128},{"name":"15w37a","protocolNumber":71,"dataNumber":127},{"name":"15w36d","protocolNumber":70,"dataNumber":126},{"name":"15w36c","protocolNumber":69,"dataNumber":125},{"name":"15w36b","protocolNumber":68,"dataNumber":124},{"name":"15w36a","protocolNumber":67,"dataNumber":123},{"name":"15w35e","protocolNumber":66,"dataNumber":122},{"name":"15w35d","protocolNumber":65,"dataNumber":121},{"name":"15w35c","protocolNumber":64,"dataNumber":120},{"name":"15w35b","protocolNumber":63,"dataNumber":119},{"name":"15w35a","protocolNumber":62,"dataNumber":118},{"name":"15w34d","protocolNumber":61,"dataNumber":117},{"name":"15w34c","protocolNumber":60,"dataNumber":116},{"name":"15w34b","protocolNumber":59,"dataNumber":115},{"name":"15w34a","protocolNumber":58,"dataNumber":114},{"name":"15w33c","protocolNumber":57,"dataNumber":112},{"name":"15w33b","protocolNumber":56,"dataNumber":111},{"name":"15w33a","protocolNumber":55,"dataNumber":111},{"name":"15w32c","protocolNumber":54,"dataNumber":104},{"name":"15w32b","protocolNumber":53,"dataNumber":103},{"name":"15w32a","protocolNumber":52,"dataNumber":100},{"name":"15w31c","protocolNumber":51,"dataNumber":null},{"name":"15w31b","protocolNumber":50,"dataNumber":null},{"name":"15w31a","protocolNumber":49,"dataNumber":null},{"name":"1.8.9","protocolNumber":47,"dataNumber":null},{"name":"1.8.8","protocolNumber":47,"dataNumber":null},{"name":"1.8.7","protocolNumber":47,"dataNumber":null},{"name":"1.8.6","protocolNumber":47,"dataNumber":null},{"name":"1.8.5","protocolNumber":47,"dataNumber":null},{"name":"1.8.4","protocolNumber":47,"dataNumber":null},{"name":"1.8.3","protocolNumber":47,"dataNumber":null},{"name":"1.8.2","protocolNumber":47,"dataNumber":null},{"name":"1.8.2-pre7","protocolNumber":47,"dataNumber":null},{"name":"1.8.2-pre6","protocolNumber":47,"dataNumber":null},{"name":"1.8.2-pre5","protocolNumber":47,"dataNumber":null},{"name":"1.8.2-pre4","protocolNumber":47,"dataNumber":null},{"name":"1.8.2-pre3","protocolNumber":47,"dataNumber":null},{"name":"1.8.2-pre2","protocolNumber":47,"dataNumber":null},{"name":"1.8.2-pre1","protocolNumber":47,"dataNumber":null},{"name":"1.8.1","protocolNumber":47,"dataNumber":null},{"name":"1.8.1-pre5","protocolNumber":47,"dataNumber":null},{"name":"1.8.1-pre4","protocolNumber":47,"dataNumber":null},{"name":"1.8.1-pre3","protocolNumber":47,"dataNumber":null},{"name":"1.8.1-pre2","protocolNumber":47,"dataNumber":null},{"name":"1.8.1-pre1","protocolNumber":47,"dataNumber":null},{"name":"1.8","protocolNumber":47,"dataNumber":null},{"name":"1.8-pre3","protocolNumber":46,"dataNumber":null},{"name":"1.8-pre2","protocolNumber":45,"dataNumber":null},{"name":"1.8-pre1","protocolNumber":44,"dataNumber":null},{"name":"14w34d","protocolNumber":43,"dataNumber":null},{"name":"14w34c","protocolNumber":42,"dataNumber":null},{"name":"14w34b","protocolNumber":41,"dataNumber":null},{"name":"14w34a","protocolNumber":40,"dataNumber":null},{"name":"14w33c","protocolNumber":39,"dataNumber":null},{"name":"14w33b","protocolNumber":38,"dataNumber":null},{"name":"14w33a","protocolNumber":37,"dataNumber":null},{"name":"14w32d","protocolNumber":36,"dataNumber":null},{"name":"14w32c","protocolNumber":35,"dataNumber":null},{"name":"14w32b","protocolNumber":34,"dataNumber":null},{"name":"14w32a","protocolNumber":33,"dataNumber":null},{"name":"14w31a","protocolNumber":32,"dataNumber":null},{"name":"14w30c","protocolNumber":31,"dataNumber":null},{"name":"14w30b","protocolNumber":30,"dataNumber":null},{"name":"14w30a","protocolNumber":30,"dataNumber":null},{"name":"14w29b","protocolNumber":29,"dataNumber":null},{"name":"14w29a","protocolNumber":29,"dataNumber":null},{"name":"14w28b","protocolNumber":28,"dataNumber":null},{"name":"14w28a","protocolNumber":27,"dataNumber":null},{"name":"14w27b","protocolNumber":26,"dataNumber":null},{"name":"14w27a","protocolNumber":26,"dataNumber":null},{"name":"14w26c","protocolNumber":25,"dataNumber":null},{"name":"14w26b","protocolNumber":24,"dataNumber":null},{"name":"14w26a","protocolNumber":23,"dataNumber":null},{"name":"14w25b","protocolNumber":22,"dataNumber":null},{"name":"14w25a","protocolNumber":21,"dataNumber":null},{"name":"14w21b","protocolNumber":20,"dataNumber":null},{"name":"14w21a","protocolNumber":19,"dataNumber":null},{"name":"14w20b","protocolNumber":18,"dataNumber":null},{"name":"14w20a","protocolNumber":18,"dataNumber":null},{"name":"14w19a","protocolNumber":17,"dataNumber":null},{"name":"14w18b","protocolNumber":16,"dataNumber":null},{"name":"14w18a","protocolNumber":16,"dataNumber":null},{"name":"14w17a","protocolNumber":15,"dataNumber":null},{"name":"14w11b","protocolNumber":14,"dataNumber":null},{"name":"14w11a","protocolNumber":14,"dataNumber":null},{"name":"14w10c","protocolNumber":13,"dataNumber":null},{"name":"14w10b","protocolNumber":13,"dataNumber":null},{"name":"14w10a","protocolNumber":13,"dataNumber":null},{"name":"14w08a","protocolNumber":12,"dataNumber":null},{"name":"14w07a","protocolNumber":11,"dataNumber":null},{"name":"14w06b","protocolNumber":10,"dataNumber":null},{"name":"14w06a","protocolNumber":10,"dataNumber":null},{"name":"14w05b","protocolNumber":9,"dataNumber":null},{"name":"14w05a","protocolNumber":9,"dataNumber":null},{"name":"14w04b","protocolNumber":8,"dataNumber":null},{"name":"14w04a","protocolNumber":7,"dataNumber":null},{"name":"14w03b","protocolNumber":6,"dataNumber":null},{"name":"14w03a","protocolNumber":6,"dataNumber":null},{"name":"14w02c","protocolNumber":5,"dataNumber":null},{"name":"14w02b","protocolNumber":5,"dataNumber":null},{"name":"14w02a","protocolNumber":5,"dataNumber":null},{"name":"1.7.10","protocolNumber":5,"dataNumber":null},{"name":"1.7.10-pre4","protocolNumber":5,"dataNumber":null},{"name":"1.7.10-pre3","protocolNumber":5,"dataNumber":null},{"name":"1.7.10-pre2","protocolNumber":5,"dataNumber":null},{"name":"1.7.10-pre1","protocolNumber":5,"dataNumber":null},{"name":"1.7.9","protocolNumber":5,"dataNumber":null},{"name":"1.7.8","protocolNumber":5,"dataNumber":null},{"name":"1.7.7","protocolNumber":5,"dataNumber":null},{"name":"1.7.6","protocolNumber":5,"dataNumber":null},{"name":"1.7.6-pre2","protocolNumber":5,"dataNumber":null},{"name":"1.7.6-pre1","protocolNumber":5,"dataNumber":null},{"name":"1.7.5","protocolNumber":4,"dataNumber":null},{"name":"1.7.4","protocolNumber":4,"dataNumber":null},{"name":"1.7.3","protocolNumber":4,"dataNumber":null},{"name":"13w49a","protocolNumber":4,"dataNumber":null},{"name":"13w48b","protocolNumber":4,"dataNumber":null},{"name":"13w48a","protocolNumber":4,"dataNumber":null},{"name":"13w47e","protocolNumber":4,"dataNumber":null},{"name":"13w47d","protocolNumber":4,"dataNumber":null},{"name":"13w47c","protocolNumber":4,"dataNumber":null},{"name":"13w47b","protocolNumber":4,"dataNumber":null},{"name":"13w47a","protocolNumber":4,"dataNumber":null},{"name":"1.7.2","protocolNumber":4,"dataNumber":null},{"name":"1.7.1","protocolNumber":3,"dataNumber":null},{"name":"1.7","protocolNumber":3,"dataNumber":null},{"name":"13w43a","protocolNumber":2,"dataNumber":null},{"name":"13w42b","protocolNumber":1,"dataNumber":null},{"name":"13w42a","protocolNumber":1,"dataNumber":null},{"name":"13w41b","protocolNumber":0,"dataNumber":null},{"name":"13w41a","protocolNumber":0,"dataNumber":null},{"name":"13w39b","protocolNumber":80,"dataNumber":null},{"name":"13w39a","protocolNumber":80,"dataNumber":null},{"name":"13w38c","protocolNumber":79,"dataNumber":null},{"name":"13w38b","protocolNumber":79,"dataNumber":null},{"name":"13w38a","protocolNumber":79,"dataNumber":null},{"name":"1.6.4","protocolNumber":78,"dataNumber":null},{"name":"1.6.3","protocolNumber":77,"dataNumber":null},{"name":"13w37b","protocolNumber":76,"dataNumber":null},{"name":"13w37a","protocolNumber":76,"dataNumber":null},{"name":"13w36b","protocolNumber":75,"dataNumber":null},{"name":"13w36a","protocolNumber":75,"dataNumber":null},{"name":"1.6.2","protocolNumber":74,"dataNumber":null},{"name":"1.6.1","protocolNumber":73,"dataNumber":null},{"name":"1.6","protocolNumber":72,"dataNumber":null},{"name":"13w26a","protocolNumber":72,"dataNumber":null},{"name":"13w25c","protocolNumber":71,"dataNumber":null},{"name":"13w25b","protocolNumber":71,"dataNumber":null},{"name":"13w25a","protocolNumber":71,"dataNumber":null},{"name":"13w24b","protocolNumber":70,"dataNumber":null},{"name":"13w24a","protocolNumber":69,"dataNumber":null},{"name":"13w23b","protocolNumber":68,"dataNumber":null},{"name":"13w23a","protocolNumber":67,"dataNumber":null},{"name":"13w22a","protocolNumber":67,"dataNumber":null},{"name":"13w21b","protocolNumber":67,"dataNumber":null},{"name":"13w21a","protocolNumber":67,"dataNumber":null},{"name":"13w19a","protocolNumber":66,"dataNumber":null},{"name":"13w18c","protocolNumber":65,"dataNumber":null},{"name":"13w18b","protocolNumber":65,"dataNumber":null},{"name":"13w18a","protocolNumber":65,"dataNumber":null},{"name":"13w17a","protocolNumber":64,"dataNumber":null},{"name":"13w16b","protocolNumber":63,"dataNumber":null},{"name":"13w16a","protocolNumber":62,"dataNumber":null},{"name":"1.5.2","protocolNumber":61,"dataNumber":null},{"name":"1.5.1","protocolNumber":60,"dataNumber":null},{"name":"13w12~","protocolNumber":60,"dataNumber":null},{"name":"13w11a","protocolNumber":60,"dataNumber":null},{"name":"1.5","protocolNumber":60,"dataNumber":null},{"name":"13w10b","protocolNumber":60,"dataNumber":null},{"name":"13w10a","protocolNumber":60,"dataNumber":null},{"name":"13w09c","protocolNumber":60,"dataNumber":null},{"name":"13w09b","protocolNumber":59,"dataNumber":null},{"name":"13w09a","protocolNumber":59,"dataNumber":null},{"name":"13w07a","protocolNumber":58,"dataNumber":null},{"name":"13w06a","protocolNumber":58,"dataNumber":null},{"name":"13w05b","protocolNumber":56,"dataNumber":null},{"name":"13w05a","protocolNumber":56,"dataNumber":null},{"name":"13w04a","protocolNumber":55,"dataNumber":null},{"name":"13w03a","protocolNumber":54,"dataNumber":null},{"name":"13w02b","protocolNumber":53,"dataNumber":null},{"name":"13w02a","protocolNumber":53,"dataNumber":null},{"name":"13w01b","protocolNumber":52,"dataNumber":null},{"name":"13w01a","protocolNumber":52,"dataNumber":null},{"name":"1.4.7","protocolNumber":51,"dataNumber":null},{"name":"1.4.6","protocolNumber":51,"dataNumber":null},{"name":"12w50b","protocolNumber":51,"dataNumber":null},{"name":"12w50a","protocolNumber":51,"dataNumber":null},{"name":"12w49a","protocolNumber":50,"dataNumber":null},{"name":"1.4.5","protocolNumber":49,"dataNumber":null},{"name":"1.4.4","protocolNumber":49,"dataNumber":null},{"name":"1.4.3","protocolNumber":48,"dataNumber":null},{"name":"1.4.2","protocolNumber":47,"dataNumber":null},{"name":"1.4.1","protocolNumber":47,"dataNumber":null},{"name":"1.4","protocolNumber":47,"dataNumber":null},{"name":"12w42b","protocolNumber":47,"dataNumber":null},{"name":"12w42a","protocolNumber":46,"dataNumber":null},{"name":"12w41b","protocolNumber":46,"dataNumber":null},{"name":"12w41a","protocolNumber":46,"dataNumber":null},{"name":"12w40b","protocolNumber":45,"dataNumber":null},{"name":"12w40a","protocolNumber":44,"dataNumber":null},{"name":"12w39b","protocolNumber":43,"dataNumber":null},{"name":"12w39a","protocolNumber":43,"dataNumber":null},{"name":"12w38b","protocolNumber":43,"dataNumber":null},{"name":"12w38a","protocolNumber":43,"dataNumber":null},{"name":"12w37a","protocolNumber":42,"dataNumber":null},{"name":"12w36a","protocolNumber":42,"dataNumber":null},{"name":"12w34b","protocolNumber":42,"dataNumber":null},{"name":"12w34a","protocolNumber":41,"dataNumber":null},{"name":"12w32a","protocolNumber":40,"dataNumber":null},{"name":"1.3.2","protocolNumber":39,"dataNumber":null},{"name":"1.3.1","protocolNumber":39,"dataNumber":null},{"name":"1.3","protocolNumber":39,"dataNumber":null},{"name":"12w30e","protocolNumber":39,"dataNumber":null},{"name":"12w30d","protocolNumber":39,"dataNumber":null},{"name":"12w30c","protocolNumber":39,"dataNumber":null},{"name":"12w30b","protocolNumber":38,"dataNumber":null},{"name":"12w30a","protocolNumber":38,"dataNumber":null},{"name":"12w27a","protocolNumber":38,"dataNumber":null},{"name":"12w26a","protocolNumber":37,"dataNumber":null},{"name":"12w25a","protocolNumber":37,"dataNumber":null},{"name":"12w24a","protocolNumber":36,"dataNumber":null},{"name":"12w23b","protocolNumber":35,"dataNumber":null},{"name":"12w23a","protocolNumber":35,"dataNumber":null},{"name":"12w22a","protocolNumber":34,"dataNumber":null},{"name":"12w21b","protocolNumber":33,"dataNumber":null},{"name":"12w21a","protocolNumber":33,"dataNumber":null},{"name":"12w19a","protocolNumber":32,"dataNumber":null},{"name":"12w18a","protocolNumber":32,"dataNumber":null},{"name":"12w17a","protocolNumber":31,"dataNumber":null},{"name":"12w16a","protocolNumber":30,"dataNumber":null},{"name":"12w15a","protocolNumber":29,"dataNumber":null},{"name":"1.2.5","protocolNumber":29,"dataNumber":null},{"name":"1.2.4","protocolNumber":29,"dataNumber":null},{"name":"1.2.3","protocolNumber":28,"dataNumber":null},{"name":"1.2.2","protocolNumber":28,"dataNumber":null},{"name":"1.2.1","protocolNumber":28,"dataNumber":null},{"name":"1.2","protocolNumber":28,"dataNumber":null},{"name":"12w08a","protocolNumber":28,"dataNumber":null},{"name":"12w07b","protocolNumber":27,"dataNumber":null},{"name":"12w07a","protocolNumber":27,"dataNumber":null},{"name":"12w06a","protocolNumber":25,"dataNumber":null},{"name":"12w05b","protocolNumber":24,"dataNumber":null},{"name":"12w05a","protocolNumber":24,"dataNumber":null},{"name":"12w04a","protocolNumber":24,"dataNumber":null},{"name":"12w03a","protocolNumber":24,"dataNumber":null},{"name":"1.1","protocolNumber":23,"dataNumber":null},{"name":"12w01a","protocolNumber":23,"dataNumber":null},{"name":"11w50a","protocolNumber":22,"dataNumber":null},{"name":"11w49a","protocolNumber":22,"dataNumber":null},{"name":"11w48a","protocolNumber":22,"dataNumber":null},{"name":"11w47a","protocolNumber":22,"dataNumber":null},{"name":"1.0.1","protocolNumber":22,"dataNumber":null},{"name":"1.0.0","protocolNumber":22,"dataNumber":null},{"name":"RC2","protocolNumber":22,"dataNumber":null},{"name":"RC1","protocolNumber":22,"dataNumber":null},{"name":"Beta 1.9-pre 6","protocolNumber":22,"dataNumber":null},{"name":"Beta 1.9-pre 5","protocolNumber":21,"dataNumber":null},{"name":"Beta 1.9-pre 4","protocolNumber":20,"dataNumber":null},{"name":"Beta 1.9-pre 3","protocolNumber":19,"dataNumber":null},{"name":"Beta 1.9-pre 2","protocolNumber":19,"dataNumber":null},{"name":"Beta 1.9-pre","protocolNumber":18,"dataNumber":null},{"name":"Beta 1.8.1","protocolNumber":17,"dataNumber":null},{"name":"Beta 1.8","protocolNumber":17,"dataNumber":null},{"name":"Beta 1.8-pre2&#160;;)","protocolNumber":16,"dataNumber":null},{"name":"Beta 1.8 Pre-release","protocolNumber":15,"dataNumber":null},{"name":"Beta 1.7.3","protocolNumber":14,"dataNumber":null},{"name":"Beta 1.7.2","protocolNumber":14,"dataNumber":null},{"name":"Beta 1.7_01","protocolNumber":14,"dataNumber":null},{"name":"Beta 1.7","protocolNumber":14,"dataNumber":null},{"name":"Beta 1.6.6","protocolNumber":13,"dataNumber":null},{"name":"Beta 1.6.5","protocolNumber":13,"dataNumber":null},{"name":"Beta 1.6.4","protocolNumber":13,"dataNumber":null},{"name":"Beta 1.6.3","protocolNumber":13,"dataNumber":null},{"name":"Beta 1.6.2","protocolNumber":13,"dataNumber":null},{"name":"Beta 1.6.1","protocolNumber":13,"dataNumber":null},{"name":"Beta 1.6","protocolNumber":13,"dataNumber":null},{"name":"Beta 1.6 Test Build 3","protocolNumber":12,"dataNumber":null},{"name":"Beta 1.5_02","protocolNumber":11,"dataNumber":null},{"name":"Beta 1.5_01","protocolNumber":11,"dataNumber":null},{"name":"Beta 1.5","protocolNumber":11,"dataNumber":null},{"name":"Beta 1.4_01","protocolNumber":10,"dataNumber":null},{"name":"Beta 1.4","protocolNumber":10,"dataNumber":null},{"name":"Beta 1.3_01","protocolNumber":9,"dataNumber":null},{"name":"Beta 1.3","protocolNumber":9,"dataNumber":null},{"name":"Beta 1.2_02","protocolNumber":8,"dataNumber":null},{"name":"Beta 1.2_01","protocolNumber":8,"dataNumber":null},{"name":"Beta 1.2","protocolNumber":8,"dataNumber":null},{"name":"Beta 1.1_02","protocolNumber":8,"dataNumber":null},{"name":"Beta 1.1_01","protocolNumber":7,"dataNumber":null},{"name":"Beta 1.1","protocolNumber":7,"dataNumber":null},{"name":"Beta 1.0.2","protocolNumber":7,"dataNumber":null},{"name":"Beta 1.0_01","protocolNumber":7,"dataNumber":null},{"name":"Beta 1.0","protocolNumber":7,"dataNumber":null},{"name":"Alpha 0.2.8","protocolNumber":6,"dataNumber":null},{"name":"Alpha 1.2.6","protocolNumber":6,"dataNumber":null},{"name":"Alpha 0.2.7","protocolNumber":6,"dataNumber":null},{"name":"Alpha 1.2.5","protocolNumber":6,"dataNumber":null},{"name":"Alpha 0.2.6_02","protocolNumber":6,"dataNumber":null},{"name":"Alpha 1.2.4_01","protocolNumber":6,"dataNumber":null},{"name":"Alpha 0.2.6_01","protocolNumber":6,"dataNumber":null},{"name":"Alpha 0.2.6","protocolNumber":6,"dataNumber":null},{"name":"Alpha 1.2.3_05","protocolNumber":6,"dataNumber":null},{"name":"Alpha 1.2.3_04","protocolNumber":5,"dataNumber":null},{"name":"Alpha 0.2.5_02","protocolNumber":5,"dataNumber":null},{"name":"Alpha 0.2.5_01","protocolNumber":5,"dataNumber":null},{"name":"Alpha 1.2.3_02","protocolNumber":5,"dataNumber":null},{"name":"Alpha 1.2.3_01","protocolNumber":5,"dataNumber":null},{"name":"Alpha 0.2.5","protocolNumber":5,"dataNumber":null},{"name":"Alpha 1.2.3","protocolNumber":5,"dataNumber":null},{"name":"Alpha 0.2.4","protocolNumber":4,"dataNumber":null},{"name":"Alpha 1.2.2","protocolNumber":4,"dataNumber":null},{"name":"Alpha 1.2.1_01","protocolNumber":3,"dataNumber":null},{"name":"Alpha 0.2.3","protocolNumber":3,"dataNumber":null},{"name":"Alpha 1.2.1","protocolNumber":3,"dataNumber":null},{"name":"Alpha 1.2.0_02","protocolNumber":3,"dataNumber":null},{"name":"Alpha 1.2.0_01","protocolNumber":3,"dataNumber":null},{"name":"Alpha 0.2.2_01","protocolNumber":3,"dataNumber":null},{"name":"Alpha 0.2.2","protocolNumber":3,"dataNumber":null},{"name":"Alpha 1.2.0","protocolNumber":3,"dataNumber":null},{"name":"Alpha 1.1.2_01","protocolNumber":2,"dataNumber":null},{"name":"Alpha 1.1.2","protocolNumber":2,"dataNumber":null},{"name":"Alpha 0.2.1","protocolNumber":2,"dataNumber":null},{"name":"Alpha 1.1.1","protocolNumber":2,"dataNumber":null},{"name":"Alpha 0.2.0_01","protocolNumber":2,"dataNumber":null},{"name":"Alpha 0.2.0","protocolNumber":2,"dataNumber":null},{"name":"Alpha 1.1.0","protocolNumber":2,"dataNumber":null},{"name":"Alpha 1.0.17_04","protocolNumber":1,"dataNumber":null},{"name":"Alpha 1.0.17_03","protocolNumber":1,"dataNumber":null},{"name":"Alpha 1.0.17_02","protocolNumber":1,"dataNumber":null},{"name":"Alpha 0.1.4","protocolNumber":1,"dataNumber":null},{"name":"Alpha 1.0.17_01","protocolNumber":null,"dataNumber":null},{"name":"Alpha 1.0.17","protocolNumber":null,"dataNumber":null},{"name":"Alpha 0.1.3","protocolNumber":14,"dataNumber":null},{"name":"Alpha 1.0.16_02","protocolNumber":14,"dataNumber":null},{"name":"Alpha 0.1.2_01","protocolNumber":14,"dataNumber":null},{"name":"Alpha 0.1.2","protocolNumber":14,"dataNumber":null},{"name":"Alpha 1.0.16_01","protocolNumber":14,"dataNumber":null},{"name":"Alpha 0.1.1","protocolNumber":14,"dataNumber":null},{"name":"Alpha 1.0.16","protocolNumber":14,"dataNumber":null},{"name":"Alpha 0.1.0","protocolNumber":13,"dataNumber":null},{"name":"Alpha 1.0.15","protocolNumber":13,"dataNumber":null},{"name":"Alpha 1.0.14","protocolNumber":12,"dataNumber":null},{"name":"Alpha 1.0.13_01","protocolNumber":12,"dataNumber":null},{"name":"Alpha 1.0.13","protocolNumber":12,"dataNumber":null},{"name":"Alpha 1.0.12","protocolNumber":11,"dataNumber":null},{"name":"Alpha 1.0.11","protocolNumber":10,"dataNumber":null},{"name":"Alpha 1.0.10","protocolNumber":10,"dataNumber":null},{"name":"Alpha 1.0.9","protocolNumber":10,"dataNumber":null},{"name":"Alpha 1.0.8_01","protocolNumber":10,"dataNumber":null},{"name":"Alpha 1.0.8","protocolNumber":10,"dataNumber":null},{"name":"Alpha 1.0.7","protocolNumber":10,"dataNumber":null},{"name":"Alpha 1.0.6_03","protocolNumber":10,"dataNumber":null},{"name":"Alpha 1.0.6_02","protocolNumber":10,"dataNumber":null},{"name":"Alpha 1.0.6_01","protocolNumber":10,"dataNumber":null},{"name":"Alpha 1.0.6","protocolNumber":10,"dataNumber":null},{"name":"Alpha 1.0.5_01","protocolNumber":10,"dataNumber":null},{"name":"Alpha 1.0.5","protocolNumber":10,"dataNumber":null},{"name":"Alpha 1.0.4","protocolNumber":null,"dataNumber":null},{"name":"Alpha 1.0.3","protocolNumber":null,"dataNumber":null},{"name":"Alpha 1.0.2_02","protocolNumber":null,"dataNumber":null},{"name":"Alpha 1.0.2_01","protocolNumber":null,"dataNumber":null},{"name":"Alpha 1.0.2","protocolNumber":null,"dataNumber":null},{"name":"Alpha 1.0.1_01","protocolNumber":null,"dataNumber":null},{"name":"Alpha 1.0.1","protocolNumber":null,"dataNumber":null},{"name":"Alpha 1.0.0","protocolNumber":null,"dataNumber":null},{"name":"Infdev","protocolNumber":null,"dataNumber":null},{"name":"Indev","protocolNumber":null,"dataNumber":null},{"name":"0.31","protocolNumber":null,"dataNumber":null},{"name":"Classic 1.10.1","protocolNumber":7,"dataNumber":null},{"name":"Classic 1.10","protocolNumber":7,"dataNumber":null},{"name":"Classic 0.30","protocolNumber":7,"dataNumber":null},{"name":"Classic 0.29_02","protocolNumber":7,"dataNumber":null},{"name":"Classic 0.29_01","protocolNumber":7,"dataNumber":null},{"name":"Classic 1.9.1","protocolNumber":null,"dataNumber":null},{"name":"Classic 0.29","protocolNumber":7,"dataNumber":null},{"name":"Classic 0.28_01","protocolNumber":7,"dataNumber":null},{"name":"Classic 1.9","protocolNumber":7,"dataNumber":null},{"name":"Classic 1.8.3","protocolNumber":7,"dataNumber":null},{"name":"Classic 0.28","protocolNumber":null,"dataNumber":null},{"name":"Classic 0.27 SURVIVAL TEST","protocolNumber":6,"dataNumber":null},{"name":"Classic 0.26 SURVIVAL TEST","protocolNumber":6,"dataNumber":null},{"name":"Classic 0.25_05 SURVIVAL TEST","protocolNumber":6,"dataNumber":null},{"name":"Classic 0.25 SURVIVAL TEST","protocolNumber":6,"dataNumber":null},{"name":"Classic 0.24_SURVIVAL_TEST_03","protocolNumber":6,"dataNumber":null},{"name":"Classic 0.24_SURVIVAL_TEST_02","protocolNumber":6,"dataNumber":null},{"name":"Classic 0.24_SURVIVAL_TEST_01","protocolNumber":6,"dataNumber":null},{"name":"Classic 0.24_SURVIVAL_TEST","protocolNumber":6,"dataNumber":null},{"name":"Classic 0.0.23a_01","protocolNumber":6,"dataNumber":null},{"name":"Classic 0.0.23a","protocolNumber":6,"dataNumber":null},{"name":"Classic 0.0.22a_05","protocolNumber":6,"dataNumber":null},{"name":"Classic 0.0.22a_04","protocolNumber":6,"dataNumber":null},{"name":"Classic 0.0.22a_03","protocolNumber":6,"dataNumber":null},{"name":"Classic 0.0.22a_02","protocolNumber":6,"dataNumber":null},{"name":"Classic 0.0.22a_01","protocolNumber":6,"dataNumber":null},{"name":"Classic 0.0.22a","protocolNumber":6,"dataNumber":null},{"name":"Classic 0.0.21a_01","protocolNumber":6,"dataNumber":null},{"name":"Classic 0.0.21a","protocolNumber":6,"dataNumber":null},{"name":"Classic 0.0.20a_02","protocolNumber":6,"dataNumber":null},{"name":"Classic 1.8.2","protocolNumber":6,"dataNumber":null},{"name":"Classic 0.0.20a_01","protocolNumber":6,"dataNumber":null},{"name":"Classic 1.8.1","protocolNumber":6,"dataNumber":null},{"name":"Classic 1.8","protocolNumber":6,"dataNumber":null},{"name":"Classic 0.0.20a","protocolNumber":null,"dataNumber":null},{"name":"Classic 1.7","protocolNumber":5,"dataNumber":null},{"name":"Classic 0.0.19a_06","protocolNumber":null,"dataNumber":null},{"name":"Classic 0.0.19a_05","protocolNumber":null,"dataNumber":null},{"name":"Classic 1.6","protocolNumber":5,"dataNumber":null},{"name":"Classic 0.0.19a_04","protocolNumber":null,"dataNumber":null},{"name":"Classic 0.0.19a_03","protocolNumber":null,"dataNumber":null},{"name":"Classic 0.0.19a_02","protocolNumber":null,"dataNumber":null},{"name":"Classic 0.0.19a_01","protocolNumber":null,"dataNumber":null},{"name":"Classic 1.5","protocolNumber":5,"dataNumber":null},{"name":"Classic 0.0.19a","protocolNumber":null,"dataNumber":null},{"name":"Classic 0.0.18a_02","protocolNumber":4,"dataNumber":null},{"name":"Classic 1.4.1","protocolNumber":4,"dataNumber":null},{"name":"Classic 0.0.18a_01","protocolNumber":null,"dataNumber":null},{"name":"Classic 0.0.18a","protocolNumber":null,"dataNumber":null},{"name":"Classic 1.4","protocolNumber":4,"dataNumber":null},{"name":"Classic 1.3","protocolNumber":4,"dataNumber":null},{"name":"Classic 0.0.17a","protocolNumber":4,"dataNumber":null},{"name":"Classic 1.2","protocolNumber":3,"dataNumber":null},{"name":"Classic 0.0.16a_02","protocolNumber":3,"dataNumber":null},{"name":"Classic 1.1","protocolNumber":null,"dataNumber":null},{"name":"Classic 0.0.16a_01","protocolNumber":null,"dataNumber":null},{"name":"Classic 1.0","protocolNumber":null,"dataNumber":null},{"name":"Classic 0.0.16a","protocolNumber":null,"dataNumber":null},{"name":"Classic 0.0.15a_03","protocolNumber":null,"dataNumber":null},{"name":"Classic 0.0.15a_02","protocolNumber":null,"dataNumber":null},{"name":"Classic 0.0.15a_01","protocolNumber":null,"dataNumber":null},{"name":"Classic 0.0.15a","protocolNumber":null,"dataNumber":null},{"name":"Classic 0.0.14a_08","protocolNumber":null,"dataNumber":null},{"name":"Classic 0.0.14a_07","protocolNumber":null,"dataNumber":null},{"name":"Classic 0.0.14a_06","protocolNumber":null,"dataNumber":null},{"name":"Classic 0.0.14a_05","protocolNumber":null,"dataNumber":null},{"name":"Classic 0.0.14a_04","protocolNumber":null,"dataNumber":null},{"name":"Classic 0.0.14a_03","protocolNumber":null,"dataNumber":null},{"name":"Classic 0.0.14a_01","protocolNumber":null,"dataNumber":null},{"name":"Classic 0.0.14a","protocolNumber":null,"dataNumber":null},{"name":"Classic 0.0.13a_03","protocolNumber":null,"dataNumber":null},{"name":"Classic 0.0.13a","protocolNumber":null,"dataNumber":null},{"name":"Classic 0.0.12a_03","protocolNumber":null,"dataNumber":null},{"name":"Classic 0.0.12a_02","protocolNumber":null,"dataNumber":null},{"name":"Classic 0.0.12a_01","protocolNumber":null,"dataNumber":null},{"name":"Classic 0.0.12a","protocolNumber":null,"dataNumber":null},{"name":"Classic 0.0.11a","protocolNumber":null,"dataNumber":null},{"name":"Classic 0.0.10a","protocolNumber":null,"dataNumber":null},{"name":"Classic 0.0.9a","protocolNumber":null,"dataNumber":null},{"name":"Classic 0.0.4a","protocolNumber":null,"dataNumber":null},{"name":"Classic 0.0.3a","protocolNumber":null,"dataNumber":null},{"name":"Classic 0.0.2a","protocolNumber":null,"dataNumber":null},{"name":"Classic 0.0.1a","protocolNumber":null,"dataNumber":null},{"name":"20w14∞","protocolNumber":709,"dataNumber":2522},{"name":"3D Shareware 1.34","protocolNumber":1,"dataNumber":1943},{"name":"1.RV-Pre1","protocolNumber":108,"dataNumber":173},{"name":"15w14a","protocolNumber":48,"dataNumber":null},{"name":"2.0","protocolNumber":90,"dataNumber":null}]},"bedrock":{"name":"Bedrock Edition","versions":[{"name":"Beta 1.17.20.22","protocolNumber":456},{"name":"Beta 1.17.20.21","protocolNumber":455},{"name":"Beta 1.17.20.20","protocolNumber":453},{"name":"1.17.10","protocolNumber":448},{"name":"Beta 1.17.10.23","protocolNumber":448},{"name":"Beta 1.17.10.22","protocolNumber":448},{"name":"Beta 1.17.10.21","protocolNumber":441},{"name":"Beta 1.17.10.20","protocolNumber":441},{"name":"1.17.2","protocolNumber":440},{"name":"1.17.1","protocolNumber":440},{"name":"1.17.0","protocolNumber":440},{"name":"Beta 1.17.0.58","protocolNumber":440},{"name":"Beta 1.17.0.56","protocolNumber":440},{"name":"Beta 1.17.0.54","protocolNumber":440},{"name":"Beta 1.17.0.52","protocolNumber":437},{"name":"Beta 1.17.0.50","protocolNumber":437},{"name":"Beta 1.16.230.56","protocolNumber":435},{"name":"Beta 1.16.230.54","protocolNumber":435},{"name":"Beta 1.16.230.52","protocolNumber":434},{"name":"Beta 1.16.230.50","protocolNumber":433},{"name":"1.16.221","protocolNumber":431},{"name":"1.16.220","protocolNumber":431},{"name":"Beta 1.16.220.52","protocolNumber":431},{"name":"Beta 1.16.220.51","protocolNumber":430},{"name":"Beta 1.16.220.50","protocolNumber":429},{"name":"1.16.210","protocolNumber":428},{"name":"Beta 1.16.210.61","protocolNumber":428},{"name":"Beta 1.16.210.60","protocolNumber":428},{"name":"Beta 1.16.210.59","protocolNumber":428},{"name":"Beta 1.16.210.58","protocolNumber":428},{"name":"Beta 1.16.210.57","protocolNumber":427},{"name":"Beta 1.16.210.56","protocolNumber":427},{"name":"Beta 1.16.210.55","protocolNumber":425},{"name":"Beta 1.16.210.54","protocolNumber":425},{"name":"Beta 1.16.210.53","protocolNumber":424},{"name":"Beta 1.16.210.51","protocolNumber":423},{"name":"Beta 1.16.210.50","protocolNumber":423},{"name":"1.16.201","protocolNumber":422},{"name":"1.16.200","protocolNumber":422},{"name":"Beta 1.16.200.57","protocolNumber":422},{"name":"Beta 1.16.200.56","protocolNumber":422},{"name":"Beta 1.16.200.55","protocolNumber":422},{"name":"Beta 1.16.200.53","protocolNumber":422},{"name":"Beta 1.16.200.52","protocolNumber":421},{"name":"Beta 1.16.200.51","protocolNumber":420},{"name":"1.16.101","protocolNumber":419},{"name":"1.16.100","protocolNumber":419},{"name":"Beta 1.16.100.60","protocolNumber":419},{"name":"Beta 1.16.100.59","protocolNumber":418},{"name":"Beta 1.16.100.58","protocolNumber":417},{"name":"Beta 1.16.100.57","protocolNumber":416},{"name":"Beta 1.16.100.56","protocolNumber":415},{"name":"Beta 1.16.100.55","protocolNumber":414},{"name":"Beta 1.16.100.54","protocolNumber":413},{"name":"Beta 1.16.100.53","protocolNumber":412},{"name":"Beta 1.16.100.52","protocolNumber":411},{"name":"Beta 1.16.100.51","protocolNumber":410},{"name":"Beta 1.16.100.50","protocolNumber":409},{"name":"Beta 1.16.30.57","protocolNumber":418},{"name":"Beta 1.16.30.56","protocolNumber":418},{"name":"Beta 1.16.30.53","protocolNumber":407},{"name":"Beta 1.16.30.52","protocolNumber":407},{"name":"1.16.61","protocolNumber":408},{"name":"1.16.60","protocolNumber":408},{"name":"1.16.50","protocolNumber":408},{"name":"1.16.42","protocolNumber":408},{"name":"1.16.40","protocolNumber":408},{"name":"1.16.21","protocolNumber":408},{"name":"1.16.20","protocolNumber":408},{"name":"Beta 1.16.20.54","protocolNumber":408},{"name":"Beta 1.16.20.53","protocolNumber":408},{"name":"Beta 1.16.20.52","protocolNumber":407},{"name":"Beta 1.16.20.50","protocolNumber":407},{"name":"1.16.10","protocolNumber":407},{"name":"1.16.1.04","protocolNumber":407},{"name":"1.16.1.03","protocolNumber":407},{"name":"1.16.1","protocolNumber":407},{"name":"1.16.0","protocolNumber":407},{"name":"Beta 1.16.0.68","protocolNumber":407},{"name":"Beta 1.16.0.67","protocolNumber":407},{"name":"Beta 1.16.0.66","protocolNumber":407},{"name":"Beta 1.16.0.64","protocolNumber":407},{"name":"Beta 1.16.0.63","protocolNumber":406},{"name":"Beta 1.16.0.61","protocolNumber":405},{"name":"Beta 1.16.0.60","protocolNumber":404},{"name":"Beta 1.16.0.59","protocolNumber":401},{"name":"Beta 1.16.0.58","protocolNumber":401},{"name":"Beta 1.16.0.57","protocolNumber":403},{"name":"Beta 1.16.0.55","protocolNumber":402},{"name":"Beta 1.16.0.53","protocolNumber":401},{"name":"Beta 1.16.0.51","protocolNumber":400},{"name":"Beta 1.15.0.56","protocolNumber":396},{"name":"Beta 1.15.0.55","protocolNumber":395},{"name":"Beta 1.15.0.54","protocolNumber":394},{"name":"Beta 1.15.0.53","protocolNumber":393},{"name":"Beta 1.15.0.51","protocolNumber":392},{"name":"Beta 1.15.0.11","protocolNumber":391},{"name":"Beta 1.15.0.9","protocolNumber":391},{"name":"Beta 1.15.0.8","protocolNumber":391},{"name":"1.14.60","protocolNumber":390},{"name":"1.14.41","protocolNumber":389},{"name":"1.14.30","protocolNumber":389},{"name":"Beta 1.14.30.51","protocolNumber":389},{"name":"1.14.20","protocolNumber":389},{"name":"Beta 1.14.25.1","protocolNumber":389},{"name":"Beta 1.14.2.51","protocolNumber":389},{"name":"Beta 1.14.2.50","protocolNumber":389},{"name":"1.14.1","protocolNumber":389},{"name":"Beta 1.14.1.3","protocolNumber":389},{"name":"Beta 1.14.1.2","protocolNumber":389},{"name":"1.14.0.12","protocolNumber":389},{"name":"1.14.0","protocolNumber":389},{"name":"Beta 1.14.0.52","protocolNumber":389},{"name":"Beta 1.14.0.51","protocolNumber":389},{"name":"Beta 1.14.0.50","protocolNumber":389},{"name":"Beta 1.14.0.6","protocolNumber":389},{"name":"Beta 1.14.0.4","protocolNumber":389},{"name":"Beta 1.14.0.3","protocolNumber":389},{"name":"Beta 1.14.0.2","protocolNumber":389},{"name":"Beta 1.14.0.1","protocolNumber":390},{"name":"1.13.3","protocolNumber":388},{"name":"1.13.2","protocolNumber":388},{"name":"1.13.1","protocolNumber":388},{"name":"1.13.0","protocolNumber":388},{"name":"Beta 1.13.0.18","protocolNumber":389},{"name":"Beta 1.13.0.17","protocolNumber":388},{"name":"Beta 1.13.0.16","protocolNumber":388},{"name":"Beta 1.13.0.15","protocolNumber":387},{"name":"Beta 1.13.0.13","protocolNumber":386},{"name":"Beta 1.13.0.9","protocolNumber":385},{"name":"Beta 1.13.0.6","protocolNumber":371},{"name":"Beta 1.13.0.5","protocolNumber":371},{"name":"Beta 1.13.0.4","protocolNumber":371},{"name":"Beta 1.13.0.2","protocolNumber":370},{"name":"Beta 1.13.0.1","protocolNumber":370},{"name":"1.12.1","protocolNumber":361},{"name":"1.12.0","protocolNumber":361},{"name":"Beta 1.12.0.14","protocolNumber":361},{"name":"Beta 1.12.0.13","protocolNumber":361},{"name":"Beta 1.12.0.12","protocolNumber":361},{"name":"Beta 1.12.0.11","protocolNumber":361},{"name":"Beta 1.12.0.10","protocolNumber":361},{"name":"Beta 1.12.0.9","protocolNumber":361},{"name":"Beta 1.12.0.6","protocolNumber":361},{"name":"Beta 1.12.0.4","protocolNumber":361},{"name":"Beta 1.12.0.3","protocolNumber":361},{"name":"Beta 1.12.0.2","protocolNumber":360},{"name":"1.11.4","protocolNumber":354},{"name":"1.11.3","protocolNumber":354},{"name":"1.11.2","protocolNumber":354},{"name":"1.11.1","protocolNumber":354},{"name":"1.11.0","protocolNumber":354},{"name":"Beta 1.11.0.10","protocolNumber":354},{"name":"Beta 1.11.0.9","protocolNumber":354},{"name":"Beta 1.11.0.8","protocolNumber":354},{"name":"Beta 1.11.0.7","protocolNumber":354},{"name":"Beta 1.11.0.5","protocolNumber":353},{"name":"Beta 1.11.0.4","protocolNumber":352},{"name":"Beta 1.11.0.3","protocolNumber":351},{"name":"Beta 1.11.0.1","protocolNumber":350},{"name":"1.10.1","protocolNumber":340},{"name":"1.10.0","protocolNumber":340},{"name":"Beta 1.10.0.4","protocolNumber":340},{"name":"Beta 1.10.0.3","protocolNumber":340},{"name":"1.9.0","protocolNumber":332},{"name":"Beta 1.9.0.5","protocolNumber":332},{"name":"Beta 1.9.0.3","protocolNumber":332},{"name":"Beta 1.9.0.2","protocolNumber":331},{"name":"Beta 1.9.0.0","protocolNumber":330},{"name":"1.8.1","protocolNumber":313},{"name":"1.8.0","protocolNumber":313},{"name":"Beta 1.8.0.14","protocolNumber":312},{"name":"Beta 1.8.0.13","protocolNumber":312},{"name":"Beta 1.8.0.11","protocolNumber":312},{"name":"Beta 1.8.0.10","protocolNumber":311},{"name":"Beta 1.8.0.8","protocolNumber":310},{"name":"1.7.1","protocolNumber":291},{"name":"1.7.0","protocolNumber":291},{"name":"Beta 1.7.0.9","protocolNumber":291},{"name":"Beta 1.7.0.7","protocolNumber":291},{"name":"Beta 1.7.0.5","protocolNumber":291},{"name":"Beta 1.7.0.3","protocolNumber":290},{"name":"Beta 1.7.0.2","protocolNumber":290},{"name":"1.6.2","protocolNumber":282},{"name":"1.6.1","protocolNumber":282},{"name":"1.6.0","protocolNumber":282},{"name":"Beta 1.6.0.30","protocolNumber":282},{"name":"Beta 1.6.0.8","protocolNumber":282},{"name":"Beta 1.6.0.6","protocolNumber":281},{"name":"Beta 1.6.0.5","protocolNumber":281},{"name":"Beta 1.6.0.1","protocolNumber":280},{"name":"1.5.3","protocolNumber":274},{"name":"1.5.2","protocolNumber":274},{"name":"1.5.1","protocolNumber":274},{"name":"1.5.0","protocolNumber":274},{"name":"Beta 1.5.0.10","protocolNumber":274},{"name":"Beta 1.5.0.7","protocolNumber":273},{"name":"Beta 1.5.0.4","protocolNumber":271},{"name":"Beta 1.5.0.1","protocolNumber":271},{"name":"Beta 1.5.0.0","protocolNumber":270},{"name":"1.4.4","protocolNumber":261},{"name":"1.4.3","protocolNumber":261},{"name":"1.4.2","protocolNumber":261},{"name":"1.4.1","protocolNumber":261},{"name":"1.4.0","protocolNumber":261},{"name":"Beta 1.2.20.2","protocolNumber":260},{"name":"Beta 1.2.20.1","protocolNumber":260},{"name":"Beta 1.2.14.3","protocolNumber":240},{"name":"Beta 1.2.14.2","protocolNumber":240},{"name":"Beta 1.2.13.12","protocolNumber":223},{"name":"Beta 1.2.13.11","protocolNumber":224},{"name":"Beta 1.2.13.10","protocolNumber":222},{"name":"Beta 1.2.13.8","protocolNumber":221},{"name":"1.2.13.60","protocolNumber":223},{"name":"1.2.15","protocolNumber":223},{"name":"1.2.14","protocolNumber":223},{"name":"1.2.13","protocolNumber":223},{"name":"Beta 1.2.13.6","protocolNumber":220},{"name":"Beta 1.2.13.5","protocolNumber":220},{"name":"1.2.11","protocolNumber":201},{"name":"1.2.10","protocolNumber":201},{"name":"Beta 1.2.10.1","protocolNumber":200},{"name":"1.2.9","protocolNumber":160},{"name":"1.2.8","protocolNumber":160},{"name":"1.2.7","protocolNumber":160},{"name":"1.2.6.1","protocolNumber":150},{"name":"1.2.6","protocolNumber":150},{"name":"Beta 1.2.6.2","protocolNumber":140},{"name":"1.2.5","protocolNumber":141},{"name":"Beta 1.2.5.15","protocolNumber":141},{"name":"Beta 1.2.5.12","protocolNumber":140},{"name":"Beta 1.2.5.0","protocolNumber":137},{"name":"1.2.3","protocolNumber":137},{"name":"Beta 1.2.3.3","protocolNumber":137},{"name":"1.2.2","protocolNumber":137},{"name":"1.2.1","protocolNumber":137},{"name":"1.2.0","protocolNumber":137},{"name":"Beta 1.2.0.31","protocolNumber":136},{"name":"Beta 1.2.0.25","protocolNumber":135},{"name":"Beta 1.2.0.22","protocolNumber":134},{"name":"Beta 1.2.0.18","protocolNumber":133},{"name":"Beta 1.2.0.15","protocolNumber":132},{"name":"Beta 1.2.0.11","protocolNumber":132},{"name":"Beta 1.2.0.9","protocolNumber":131},{"name":"Beta 1.2.0.7","protocolNumber":131},{"name":"Beta 1.2.0.2","protocolNumber":130},{"name":"1.1.7","protocolNumber":113},{"name":"1.1.5","protocolNumber":113},{"name":"1.1.4","protocolNumber":113},{"name":"1.1.3","protocolNumber":113},{"name":"Alpha 1.1.3.1","protocolNumber":113},{"name":"Alpha 1.1.3.0","protocolNumber":113},{"name":"1.1.2","protocolNumber":113},{"name":"1.1.1","protocolNumber":113},{"name":"Alpha 1.1.1.1","protocolNumber":113},{"name":"Alpha 1.1.1.0","protocolNumber":113},{"name":"1.1.0","protocolNumber":113},{"name":"Alpha 1.1.0.9","protocolNumber":112},{"name":"Alpha 1.1.0.8","protocolNumber":111},{"name":"Alpha 1.1.0.5","protocolNumber":110},{"name":"Alpha 1.1.0.4","protocolNumber":110},{"name":"Alpha 1.1.0.3","protocolNumber":110},{"name":"Alpha 1.1.0.1","protocolNumber":110},{"name":"Alpha 1.1.0.0","protocolNumber":110},{"name":"1.0.9","protocolNumber":107},{"name":"1.0.8","protocolNumber":107},{"name":"1.0.7","protocolNumber":107},{"name":"1.0.6","protocolNumber":106},{"name":"Alpha 1.0.6.0","protocolNumber":105},{"name":"1.0.5","protocolNumber":105},{"name":"Alpha 1.0.5.11","protocolNumber":105},{"name":"Alpha 1.0.5.3","protocolNumber":105},{"name":"Alpha 1.0.5.0","protocolNumber":105},{"name":"1.0.4","protocolNumber":102},{"name":"Alpha 1.0.4.1","protocolNumber":102},{"name":"Alpha 1.0.4.0","protocolNumber":101},{"name":"1.0.3","protocolNumber":101},{"name":"Alpha 1.0.3.0","protocolNumber":101},{"name":"1.0.2","protocolNumber":100},{"name":"1.0.1","protocolNumber":100},{"name":"1.0.0","protocolNumber":100},{"name":"Alpha 1.0.0.7","protocolNumber":100},{"name":"Alpha 1.0.0.2","protocolNumber":100},{"name":"Alpha 1.0.0.1","protocolNumber":92},{"name":"Alpha 1.0.0.0","protocolNumber":92},{"name":"Alpha 0.17.0.2","protocolNumber":91},{"name":"Alpha 0.17.0.1","protocolNumber":91},{"name":"0.16.2","protocolNumber":91},{"name":"0.16.1","protocolNumber":91},{"name":"0.16.0","protocolNumber":91},{"name":"0.16.0 Alpha build 5","protocolNumber":90},{"name":"0.16.0 Alpha build 4","protocolNumber":90},{"name":"0.16.0 Alpha build 3","protocolNumber":90},{"name":"0.16.0 Alpha build 2","protocolNumber":90},{"name":"0.16.0 Alpha build 1","protocolNumber":90},{"name":"0.15.90.1 Alpha build 1","protocolNumber":90},{"name":"0.15.90 Alpha build 1","protocolNumber":90},{"name":"0.15.10","protocolNumber":84},{"name":"0.15.9","protocolNumber":83},{"name":"0.15.8","protocolNumber":82},{"name":"0.15.7","protocolNumber":82},{"name":"0.15.6","protocolNumber":82},{"name":"0.15.4","protocolNumber":82},{"name":"0.15.3","protocolNumber":81},{"name":"0.15.2","protocolNumber":81},{"name":"0.15.1","protocolNumber":81},{"name":"0.15.1 Alpha build 1","protocolNumber":81},{"name":"0.15.0","protocolNumber":81},{"name":"0.15.0 Alpha build 3","protocolNumber":81},{"name":"0.15.0 Alpha build 2","protocolNumber":81},{"name":"0.15.0 Alpha build 1","protocolNumber":81},{"name":"Alpha Realms build 4","protocolNumber":60},{"name":"Alpha Realms build 2","protocolNumber":60},{"name":"Alpha Realms build 1","protocolNumber":60},{"name":"0.14.3","protocolNumber":70},{"name":"0.14.2","protocolNumber":60},{"name":"0.14.1","protocolNumber":46},{"name":"0.14.0","protocolNumber":45},{"name":"0.14.0 Alpha build 7","protocolNumber":45},{"name":"0.14.0 Alpha build 6","protocolNumber":44},{"name":"0.14.0 Alpha build 5","protocolNumber":43},{"name":"0.14.0 Alpha build 4","protocolNumber":43},{"name":"0.14.0 Alpha build 3","protocolNumber":42},{"name":"0.14.0 Alpha build 2","protocolNumber":41},{"name":"0.14.0 Alpha build 1","protocolNumber":41},{"name":"0.13.2 alpha","protocolNumber":39},{"name":"0.13.1 alpha","protocolNumber":null},{"name":"0.13.0 alpha","protocolNumber":null},{"name":"0.13.0 Alpha build 5","protocolNumber":38},{"name":"0.13.0 Alpha build 4","protocolNumber":38},{"name":"0.13.0 Alpha build 3","protocolNumber":38},{"name":"0.13.0 Alpha build 2","protocolNumber":37},{"name":"0.13.0 Alpha build 1","protocolNumber":37},{"name":"0.12.3 alpha","protocolNumber":null},{"name":"0.12.2 alpha","protocolNumber":null},{"name":"0.12.1 alpha","protocolNumber":null},{"name":"0.12.1 Alpha build 13","protocolNumber":34},{"name":"0.12.1 Alpha build 12","protocolNumber":34},{"name":"0.12.1 Alpha build 11","protocolNumber":34},{"name":"0.12.1 Alpha build 10","protocolNumber":34},{"name":"0.12.1 Alpha build 9","protocolNumber":null},{"name":"0.12.1 Alpha build 8","protocolNumber":null},{"name":"0.12.1 Alpha build 7","protocolNumber":null},{"name":"0.12.1 Alpha build 6","protocolNumber":null},{"name":"0.12.1 Alpha build 5","protocolNumber":null},{"name":"0.12.1 Alpha build 4","protocolNumber":null},{"name":"0.12.1 Alpha build 3","protocolNumber":null},{"name":"0.12.1 Alpha build 2","protocolNumber":null},{"name":"0.12.1 Alpha build 1","protocolNumber":null},{"name":"0.12.0.1 alpha","protocolNumber":null},{"name":"0.12.0 alpha","protocolNumber":null},{"name":"0.11.2 alpha","protocolNumber":null},{"name":"0.11.1 alpha","protocolNumber":null},{"name":"0.11.0 alpha","protocolNumber":null},{"name":"0.11.0 Alpha build 14","protocolNumber":27},{"name":"0.11.0 Alpha build 13","protocolNumber":null},{"name":"0.11.0 Alpha build 12","protocolNumber":null},{"name":"0.11.0 Alpha build 11","protocolNumber":26},{"name":"0.11.0 Alpha build 10","protocolNumber":null},{"name":"0.11.0 Alpha build 9","protocolNumber":null},{"name":"0.11.0 Alpha build 8","protocolNumber":25},{"name":"0.11.0 Alpha build 7","protocolNumber":24},{"name":"0.11.0 Alpha build 6","protocolNumber":null},{"name":"0.11.0 Alpha build 5","protocolNumber":23},{"name":"0.11.0 Alpha build 4","protocolNumber":22},{"name":"0.11.0 Alpha build 3","protocolNumber":null},{"name":"0.11.0 Alpha build 2","protocolNumber":null},{"name":"0.11.0 Alpha build 1","protocolNumber":21},{"name":"0.10.5 alpha","protocolNumber":null},{"name":"0.10.4 alpha","protocolNumber":null},{"name":"0.10.3 alpha","protocolNumber":null},{"name":"0.10.2 alpha","protocolNumber":null},{"name":"0.10.1 alpha","protocolNumber":null},{"name":"0.10.0 alpha","protocolNumber":null},{"name":"0.10.0 Alpha build 9","protocolNumber":null},{"name":"0.10.0 Alpha build 8","protocolNumber":null},{"name":"0.10.0 Alpha build 7","protocolNumber":null},{"name":"0.10.0 Alpha build 6","protocolNumber":20},{"name":"0.10.0 Alpha build 5","protocolNumber":null},{"name":"0.10.0 Alpha build 4","protocolNumber":null},{"name":"0.10.0 Alpha build 3","protocolNumber":null},{"name":"0.10.0 Alpha build 2","protocolNumber":null},{"name":"0.10.0 Alpha build 1","protocolNumber":19},{"name":"0.9.5 alpha","protocolNumber":18},{"name":"0.9.4 alpha","protocolNumber":null},{"name":"0.9.3 alpha","protocolNumber":null},{"name":"0.9.2 alpha","protocolNumber":null},{"name":"0.9.1 alpha","protocolNumber":null},{"name":"0.9.0 alpha","protocolNumber":null},{"name":"0.9.0 Alpha build 12","protocolNumber":17},{"name":"0.9.0 Alpha build 11","protocolNumber":null},{"name":"0.9.0 Alpha build 10","protocolNumber":null},{"name":"0.9.0 Alpha build 9","protocolNumber":null},{"name":"0.9.0 Alpha build 8","protocolNumber":null},{"name":"0.9.0 Alpha build 7","protocolNumber":16},{"name":"0.9.0 Alpha build 6","protocolNumber":null},{"name":"0.9.0 Alpha build 5","protocolNumber":null},{"name":"0.9.0 Alpha build 4","protocolNumber":null},{"name":"0.9.0 Alpha build 3","protocolNumber":null},{"name":"0.9.0 Alpha build 2","protocolNumber":15},{"name":"0.9.0 Alpha build 1","protocolNumber":null},{"name":"0.8.2 alpha","protocolNumber":null},{"name":"0.8.1 alpha","protocolNumber":14},{"name":"0.8.0 alpha","protocolNumber":null},{"name":"0.8.0 Alpha build 8","protocolNumber":null},{"name":"0.8.0 Alpha build 7","protocolNumber":null},{"name":"0.8.0 Alpha build 6","protocolNumber":null},{"name":"0.8.0 Alpha build 5","protocolNumber":null},{"name":"0.8.0 Alpha build 4","protocolNumber":null},{"name":"0.8.0 Alpha build 3","protocolNumber":null},{"name":"0.8.0 Alpha build 2","protocolNumber":null},{"name":"0.7.6 alpha","protocolNumber":null},{"name":"0.7.5 alpha","protocolNumber":null},{"name":"0.7.4 alpha","protocolNumber":12},{"name":"0.7.3 alpha","protocolNumber":null},{"name":"0.7.2 alpha","protocolNumber":null},{"name":"0.7.1 alpha","protocolNumber":null},{"name":"0.7.0 alpha","protocolNumber":11},{"name":"0.6.1 alpha","protocolNumber":9},{"name":"0.6.0 alpha","protocolNumber":9},{"name":"0.5.0 alpha","protocolNumber":8},{"name":"0.4.0 Alpha rev 3","protocolNumber":null},{"name":"0.4.0 Alpha rev 2","protocolNumber":null},{"name":"0.4.0 alpha","protocolNumber":7},{"name":"0.3.3 alpha","protocolNumber":6},{"name":"0.3.2 alpha","protocolNumber":5},{"name":"0.3.0 alpha","protocolNumber":4},{"name":"0.2.2 alpha","protocolNumber":3},{"name":"0.2.1 alpha2","protocolNumber":null},{"name":"0.2.1 alpha","protocolNumber":3},{"name":"0.2.0 alpha","protocolNumber":2},{"name":"0.1.3 alpha","protocolNumber":null},{"name":"0.1.2 alpha","protocolNumber":null},{"name":"0.1.1 alpha","protocolNumber":null},{"name":"0.1.0 alpha","protocolNumber":null},{"name":"Demo","protocolNumber":null}]},"education":{"name":"Education Edition","versions":[{"name":"1.14.70","protocolNumber":392},{"name":"1.14.60","protocolNumber":392},{"name":"1.14.50","protocolNumber":391},{"name":"1.14.40","protocolNumber":391},{"name":"1.14.32","protocolNumber":390},{"name":"1.14.31","protocolNumber":390},{"name":"1.14.30","protocolNumber":390},{"name":"1.12.60","protocolNumber":363},{"name":"1.12.5","protocolNumber":null},{"name":"1.12.3","protocolNumber":362},{"name":"1.12.1","protocolNumber":null},{"name":"1.12.0","protocolNumber":361},{"name":"1.9.3","protocolNumber":332},{"name":"1.9.1","protocolNumber":332},{"name":"1.9","protocolNumber":332},{"name":"1.8.0","protocolNumber":332},{"name":"1.7.3","protocolNumber":291},{"name":"1.7.1","protocolNumber":291},{"name":"1.7","protocolNumber":291},{"name":"1.4","protocolNumber":261},{"name":"1.0.28","protocolNumber":150},{"name":"1.0.27","protocolNumber":150},{"name":"1.0.21","protocolNumber":137},{"name":"1.0.18","protocolNumber":null},{"name":"1.0.17","protocolNumber":null},{"name":"1.0.2","protocolNumber":137},{"name":"1.0.1","protocolNumber":null},{"name":"1.0.0","protocolNumber":null},{"name":"0.16.0","protocolNumber":null},{"name":"0.14.2","protocolNumber":null}]}}}
